opensi/__init__.py
opensi/pipeline.py
opensi/domain_adaptation/__init__.py
opensi/domain_adaptation/optimal_transport.py
opensi/feature_selection/__init__.py
opensi/feature_selection/lasso.py
opensi/feature_selection/seqfs.py
opensi/node/__init__.py
opensi/node/data.py
opensi/test_statistics/__init__.py
opensi/test_statistics/fs.py
opensi/test_statistics/fs_after_da.py
opensi/util/__init__.py
opensi/util/util.py
pyselectinf-0.0.1.post2.dist-info/licenses/LICENSE
pythonsi/__init__.py
pythonsi/pipeline.py
pythonsi/domain_adaptation/__init__.py
pythonsi/domain_adaptation/optimal_transport.py
pythonsi/feature_selection/__init__.py
pythonsi/feature_selection/lasso.py
pythonsi/feature_selection/seqfs.py
pythonsi/node/__init__.py
pythonsi/node/data.py
pythonsi/test_statistics/__init__.py
pythonsi/test_statistics/fs.py
pythonsi/test_statistics/fs_after_da.py
pythonsi/util/__init__.py
pythonsi/util/util.py
si/__init__.py
si/pipeline.py
si/domain_adaptation/__init__.py
si/domain_adaptation/optimal_transport.py
si/feature_selection/__init__.py
si/feature_selection/lasso.py
si/feature_selection/seqfs.py
si/node/__init__.py
si/node/data.py
si/test_statistics/__init__.py
si/test_statistics/fs.py
si/test_statistics/fs_after_da.py
si/util/__init__.py
si/util/util.py
pyselectinf-0.0.1.post2.dist-info/METADATA
pyselectinf-0.0.1.post2.dist-info/WHEEL
pyselectinf-0.0.1.post2.dist-info/top_level.txt
pyselectinf-0.0.1.post2.dist-info/RECORD
